i18n/__init__.py
i18n/config.py
i18n/custom_functions.py
i18n/errors.py
i18n/formatters.py
i18n/py.typed
i18n/resource_loader.py
i18n/translations.py
i18n/translator.py
i18n/loaders/__init__.py
i18n/loaders/json_loader.py
i18n/loaders/loader.py
i18n/loaders/python_loader.py
i18n/loaders/yaml_loader.py
i18nice-0.16.0.dist-info/licenses/LICENSE
i18nice-0.16.0.dist-info/METADATA
i18nice-0.16.0.dist-info/WHEEL
i18nice-0.16.0.dist-info/top_level.txt
i18nice-0.16.0.dist-info/zip-safe
i18nice-0.16.0.dist-info/RECORD
