Metadata-Version: 2.4
Name: i18nice
Version: 0.16.0
Summary: Translation library for Python
Home-page: https://github.com/solaluset/i18nice
Download-URL: https://github.com/solaluset/i18nice/archive/master.zip
Author: Daniel Perez
Author-email: tuvistavie@gmail.com
Maintainer: Sola Luset
License: MIT
Classifier: Development Status :: 5 - Production/Stable
Classifier: Environment :: Other Environment
Classifier: Intended Audience :: Developers
Classifier: License :: OSI Approved :: MIT License
Classifier: Operating System :: OS Independent
Classifier: Programming Language :: Python :: 3
Classifier: Topic :: Software Development :: Libraries
Classifier: Topic :: Software Development :: Internationalization
License-File: LICENSE
Provides-Extra: yaml
Requires-Dist: pyyaml>=3.10; extra == "yaml"
Dynamic: author
Dynamic: author-email
Dynamic: classifier
Dynamic: description
Dynamic: description-content-type
Dynamic: download-url
Dynamic: home-page
Dynamic: license
Dynamic: license-file
Dynamic: maintainer
Dynamic: provides-extra
Dynamic: summary
